README
hgcanttype.py
setup.py
hgcanttype.egg-info/PKG-INFO
hgcanttype.egg-info/SOURCES.txt
hgcanttype.egg-info/dependency_links.txt
hgcanttype.egg-info/top_level.txt