Metadata-Version: 1.0
Name: hgcanttype
Version: 1.0.7
Summary: Typo handler for Mercurial commands
Home-page: http://bitbucket.org/getoffmalawn/hgcanttype
Author: Nathan Hoad
Author-email: nathan@getoffmalawn.com
License: GPLv2+
Keywords: hg mercurial
Platform: UNKNOWN
